MANIFEST.in
README.md
conf.py
setup.py
version.py
repo_splitter/__init__.py
repo_splitter/__main__.py
repo_splitter/config.py
repo_splitter.egg-info/PKG-INFO
repo_splitter.egg-info/SOURCES.txt
repo_splitter.egg-info/dependency_links.txt
repo_splitter.egg-info/entry_points.txt
repo_splitter.egg-info/requires.txt
repo_splitter.egg-info/top_level.txt
repo_splitter/git_tools/__init__.py
repo_splitter/git_tools/clone.py
repo_splitter/git_tools/history.py
repo_splitter/git_tools/push.py
repo_splitter/git_tools/remote.py
repo_splitter/git_tools/track.py
repo_splitter/git_tools/url.py
repo_splitter/git_tools/files/__init__.py
repo_splitter/git_tools/files/all.py
repo_splitter/git_tools/files/renames.py
repo_splitter/git_tools/files/unwanted.py
repo_splitter/git_tools/files/wanted.py
repo_splitter/github_tools/__init__.py
repo_splitter/github_tools/connect.py
repo_splitter/github_tools/create.py
repo_splitter/github_tools/query.py
repo_splitter/gui/__init__.py
repo_splitter/gui/config.py
repo_splitter/gui/error.py
repo_splitter/gui/loading.py
repo_splitter/gui/main.py