Metadata-Version: 2.1
Name: repo-splitter
Version: 0.4.1
Summary: A GUI and CLI tool to split a part of a git repo into another git repo, separating the history
Home-page: https://github.com/nickderobertis/repo-splitter/
Author: Nick DeRobertis
Author-email: whoopnip@gmail.com
License: MIT
Project-URL: Code, https://github.com/nickderobertis/repo-splitter/
Project-URL: Documentation, https://nickderobertis.github.io/repo-splitter/
Platform: UNKNOWN
Classifier: Development Status :: 3 - Alpha
Classifier: Intended Audience :: Developers
Classifier: Programming Language :: Python :: 3.6
Classifier: Programming Language :: Python :: 3.7
Provides-Extra: Qt
